{"trial_id": "0006", "hyperparameters": {"space": [{"class_name": "Int", "config": {"name": "units", "default": null, "conditions": [], "min_value": 4, "max_value": 32, "step": 4, "sampling": null}}, {"class_name": "Choice", "config": {"name": "learningRate", "default": 0.01, "conditions": [], "values": [0.01, 0.001, 0.0001], "ordered": true}}, {"class_name": "Choice", "config": {"name": "dropoutRate", "default": 0.0, "conditions": [], "values": [0.0, 0.1, 0.2], "ordered": true}}], "values": {"units": 32, "learningRate": 0.01, "dropoutRate": 0.2, "tuner/epochs": 2, "tuner/initial_epoch": 0, "tuner/bracket": 4, "tuner/round": 0}}, "metrics": {"metrics": {"loss": {"direction": "min", "observations": [{"value": [14.732416152954102], "step": 1}]}, "asymm_mse": {"direction": "min", "observations": [{"value": [14.732416152954102], "step": 1}]}, "val_loss": {"direction": "min", "observations": [{"value": [16.149911880493164], "step": 1}]}, "val_asymm_mse": {"direction": "min", "observations": [{"value": [16.149911880493164], "step": 1}]}}}, "score": 14.732416152954102, "best_step": 1, "status": "COMPLETED"}